Metadata-Version: 1.0
Name: BinoGauss-Probability
Version: 1.2
Summary: Gaussian distributions
Home-page: UNKNOWN
Author: UNKNOWN
Author-email: UNKNOWN
License: UNKNOWN
Platform: UNKNOWN
